{
  "schemaVersion": 1,
  "id": "tc-uhc",
  "version": "1.0.0",

  "name": "TC UHC in fabric",
  "description": "",
  "authors": [
    "Fallen_Breath"
  ],
  "contact": {
    "homepage": "https://www.curseforge.com/",
    "sources": "https://github.com/"
  },

  "icon": "assets/tcuhc/icon.png",

  "environment": "*",
  "entrypoints": {
    "main": [
    ]
  },
  "mixins": [
    "tcuhc.mixins.json"
  ],

  "depends": {
    "fabricloader": ">=0.7.1",
    "minecraft": "1.15.x"
  },
  "suggests": {
    "flamingo": "*"
  }
}
